.coveragerc
.gitignore
CHANGES.rst
MANIFEST.in
README.rst
bootstrap.py
buildout.cfg
setup.py
src/collective/__init__.py
src/collective.envlogfile.egg-info/PKG-INFO
src/collective.envlogfile.egg-info/SOURCES.txt
src/collective.envlogfile.egg-info/dependency_links.txt
src/collective.envlogfile.egg-info/entry_points.txt
src/collective.envlogfile.egg-info/namespace_packages.txt
src/collective.envlogfile.egg-info/not-zip-safe
src/collective.envlogfile.egg-info/requires.txt
src/collective.envlogfile.egg-info/top_level.txt
src/collective/envlogfile/__init__.py
src/collective/envlogfile/component.xml
src/collective/envlogfile/configure.zcml
src/collective/envlogfile/handlers.py