Metadata-Version: 1.1
Name: collective.envlogfile
Version: 1.0.0
Summary: UNKNOWN
Home-page: https://github.com/datakurre/collective.envlogfile
Author: Asko Soukka
Author-email: asko.soukka@iki.fi
License: EUPL
Platform: UNKNOWN
Classifier: Programming Language :: Python
